awslabs/__init__.py
awslabs/kinesis_mcp_server/__init__.py
awslabs/kinesis_mcp_server/common.py
awslabs/kinesis_mcp_server/consts.py
awslabs/kinesis_mcp_server/server.py
awslabs_kinesis_mcp_server-0.1.2.dist-info/METADATA
awslabs_kinesis_mcp_server-0.1.2.dist-info/WHEEL
awslabs_kinesis_mcp_server-0.1.2.dist-info/entry_points.txt
awslabs_kinesis_mcp_server-0.1.2.dist-info/licenses/LICENSE
awslabs_kinesis_mcp_server-0.1.2.dist-info/licenses/NOTICE
awslabs_kinesis_mcp_server-0.1.2.dist-info/RECORD
